dash_charts/__init__.py
dash_charts/app_px.py
dash_charts/assets/09_user-styles.css
dash_charts/assets/README.txt
dash_charts/assets/favicon.ico
dash_charts/components.py
dash_charts/coordinate_chart.py
dash_charts/custom_colorscales.py
dash_charts/datatable.py
dash_charts/equations.py
dash_charts/gantt_chart.py
dash_charts/modules_datatable.py
dash_charts/modules_upload.py
dash_charts/pareto_chart.py
dash_charts/scatter_line_charts.py
dash_charts/time_vis_chart.py
dash_charts/utils_app.py
dash_charts/utils_app_modules.py
dash_charts/utils_app_with_navigation.py
dash_charts/utils_callbacks.py
dash_charts/utils_data.py
dash_charts/utils_dataset.py
dash_charts/utils_fig.py
dash_charts/utils_helpers.py
dash_charts/utils_json_cache.py
dash_charts/utils_static.py
dash_charts/utils_static_toc.py
dash_charts-0.1.2.dist-info/LICENSE
dash_charts-0.1.2.dist-info/WHEEL
dash_charts-0.1.2.dist-info/METADATA
dash_charts-0.1.2.dist-info/RECORD
