Metadata-Version: 2.1
Name: dash-charts
Version: 0.1.2
Summary: Python package for Plotly/Dash apps with support for multi-page, modules, and new charts such as Pareto with an Object Orient Approach
Home-page: https://github.com/kyleking/dash_charts
License: MIT
Keywords: plotly-dash,plotly-python
Author: Kyle King
Author-email: dev.act.kyle@gmail.com
Requires-Python: >=3.8,<4.0
Classifier: Development Status :: 2 - Pre-Alpha
Classifier: Environment :: Web Environment
Classifier: Framework :: Dash
Classifier: Intended Audience :: Developers
Classifier: License :: OSI Approved :: MIT License
Classifier: Operating System :: OS Independent
Classifier: Programming Language :: Python :: 3
Classifier: Programming Language :: Python :: 3.10
Classifier: Programming Language :: Python :: 3.8
Classifier: Programming Language :: Python :: 3.9
Classifier: Topic :: Database :: Front-Ends
Classifier: Topic :: Scientific/Engineering :: Visualization
Classifier: Topic :: Software Development :: Libraries :: Application Frameworks
Provides-Extra: matplotlib
Requires-Dist: Palettable (>=3.3.0)
Requires-Dist: astor (>=0.8.1)
Requires-Dist: attrs-strict (>=0.2.2)
Requires-Dist: beautifulsoup4 (>=4.10.0)
Requires-Dist: calcipy (>=0.11.0)
Requires-Dist: cerberus (>=1.3.4)
Requires-Dist: dash-bootstrap-components (>=1.0.0)
Requires-Dist: dash-extensions (>=0.0.55)
Requires-Dist: dash-tabulator (>=0.4.2)
Requires-Dist: dash[testing] (>=2.0.0)
Requires-Dist: dataset (>=1.5.2)
Requires-Dist: dominate (>=2.6.0)
Requires-Dist: implements (>=0.3.0)
Requires-Dist: jsonpickle (>=2.1.0)
Requires-Dist: lxml (>=4.7.1)
Requires-Dist: markdown (>=3.3.6)
Requires-Dist: numpy (>=1.22.2)
Requires-Dist: pandas (>=1.3.0)
Requires-Dist: psutil (>=5.9.0)
Requires-Dist: python-box (>=5.4.1)
Requires-Dist: scipy (>=1.6.1)
Requires-Dist: tqdm (>=4.62.3)
Project-URL: Bug Tracker, https://github.com/kyleking/dash_charts/issues
Project-URL: Changelog, https://github.com/kyleking/dash_charts/blob/main/docs/docs/CHANGELOG.md
Project-URL: Documentation, https://github.com/kyleking/dash_charts/docs
Project-URL: Repository, https://github.com/kyleking/dash_charts
